rootconfig/__init__.py
rootconfig/rootconfig.py
rootconfig-1.0.0.dist-info/LICENSE
rootconfig-1.0.0.dist-info/METADATA
rootconfig-1.0.0.dist-info/WHEEL
rootconfig-1.0.0.dist-info/top_level.txt
rootconfig-1.0.0.dist-info/RECORD
