Metadata-Version: 2.1
Name: rootconfig
Version: 1.0.0
Author: Hanzhi Yin
Author-email: yinhanzhi@gmail.com
License: MIT License
Project-URL: repository, https://github.com/int0thewind/rootconfig
Classifier: Programming Language :: Python :: 3
Classifier: Programming Language :: Python :: 3.10
Classifier: Programming Language :: Python :: 3.11
Requires-Python: >=3.10
License-File: LICENSE
